jsonstore/__init__.py
jsonstore/__main__.py
jsonstore/msg.py
jsonstore/storage.py
jsonstore/util.py
myjsonstore-1.0.0.dist-info/DESCRIPTION.rst
myjsonstore-1.0.0.dist-info/METADATA
myjsonstore-1.0.0.dist-info/RECORD
myjsonstore-1.0.0.dist-info/WHEEL
myjsonstore-1.0.0.dist-info/metadata.json
myjsonstore-1.0.0.dist-info/top_level.txt
