Metadata-Version: 2.0
Name: myjsonstore
Version: 1.0.0
Summary: A wrapper for the popular json-store-client library - a client for jsonstore.io
Home-page: https://github.com/AgeOfMarcus/myjsonstore
Author: Marcus Weinberger
Author-email: marcus@marcusweinberger.com
License: GPL
Platform: UNKNOWN
Requires-Dist: json-store-client
